{"pageid": 246699, "ns": 0, "title": "Mamitu", "extract": "<p><b>Mamitu</b>, also known as <b>Mammetun</b>, <b>Mammetum</b>, or <b>Mammitu</b> was the ancient Akkadian goddess of fate and destiny. She was believed to reside in Irkalla and decree the fates of all human beings based on arbitrary whims. Nonetheless, whatever decrees she issued were irrevocable. She was also worshipped as goddess of the oath, later a chthonic goddess of fate and a judge in the underworld, similar to the Anunnaki. She is occasionally regarded as a consort of Nergal. In some passages, she is also known as a demon of irrevocable curses.</p>", "images": [{"ns": 6, "title": "File:Chaos Monster and Sun God.png"}, {"ns": 6, "title": "File:Palm tree symbol.svg"}, {"ns": 6, "title": "File:Question book-new.svg"}]}