{"pageid": 678477, "ns": 0, "title": "Ningal", "extract": "<p><b>Ningal</b> (<span title=\"cuneiform text\" lang=\"und-Xsux\" xml:lang=\"und-Xsux\">\ud808\udc2d\ud808\udea9\ud808\udf06\ud808\udcf2</span> <span title=\"Cuneiform transliteration\"><sup>D</sup>NIN.GAL</span>, \"Great Lady/Queen\") was a goddess of reeds in the Sumerian mythology, daughter of Enki and Ningikurga and the consort of the moon god Nanna by whom she bore the sun god Utu, his sister Inanna, and in some texts, Ishkur. She is chiefly recognised at Ur, and was probably first worshipped by cow-herders in the marsh lands of southern Mesopotamia.</p>\n<p><br></p>\n<h2><span id=\"References\">References</span></h2>\n<ul><li><cite class=\"citation book\">Jordan, Michael (2002). <i>Encyclopedia of Gods</i>. Kyle Cathie.</cite><span title=\"ctx_ver=Z39.88-2004&amp;rfr_id=info%3Asid%2Fen.wikipedia.org%3ANingal&amp;rft.aufirst=Michael&amp;rft.aulast=Jordan&amp;rft.btitle=Encyclopedia+of+Gods&amp;rft.date=2002&amp;rft.genre=book&amp;rft.pub=Kyle+Cathie&amp;rft_val_fmt=info%3Aofi%2Ffmt%3Akev%3Amtx%3Abook\"><span>\u00a0</span></span></li>\n</ul><p><br></p>\n\n<p><br></p>", "images": [{"ns": 6, "title": "File:Chaos Monster and Sun God.png"}, {"ns": 6, "title": "File:Ea (Babilonian) - EnKi (Sumerian).jpg"}, {"ns": 6, "title": "File:Palm tree symbol.svg"}]}